shining_pebbles/__init__.py
shining_pebbles/date_utils/__init__.py
shining_pebbles/date_utils/date_converter_utils.py
shining_pebbles/date_utils/date_extracting_utils.py
shining_pebbles/date_utils/date_general_utils.py
shining_pebbles/pseudo_database/__init__.py
shining_pebbles/pseudo_database/delete_utils.py
shining_pebbles/pseudo_database/file_control_utils.py
shining_pebbles/pseudo_database/file_managing_utils.py
shining_pebbles/pseudo_database/file_scan_utils.py
shining_pebbles/pseudo_database/load_utils.py
shining_pebbles-0.5.5.dist-info/METADATA
shining_pebbles-0.5.5.dist-info/WHEEL
shining_pebbles-0.5.5.dist-info/top_level.txt
shining_pebbles-0.5.5.dist-info/RECORD
