Metadata-Version: 2.1
Name: shining-pebbles
Version: 0.5.5
Summary: A collection of utility functions that enable treating a file system of multiple files as a pseudo-database, facilitating maintenance and operations across the large-scale file system. My shining pebbles.
Home-page: https://github.com/nailen1/shining_pebbles
Author: June Young Park
Author-email: juneyoungpaak@gmail.com
Project-URL: Source, https://github.com/nailen1/shining_pebbles
Classifier: Programming Language :: Python :: 3
Classifier: License :: OSI Approved :: MIT License
Classifier: Operating System :: OS Independent
Requires-Python: >=3.6
Requires-Dist: numpy>=1.21.0
Requires-Dist: pandas
Requires-Dist: python-dateutil
Requires-Dist: pybind11>=2.12
Requires-Dist: aws-s3-controller>=0.7.3
Requires-Dist: openpyxl>=3.1.5
